LICENSE
README.md
setup.py
./chain_processors/__init__.py
./chain_processors/run_example.py
./chain_processors/example/__init__.py
./chain_processors/example/query_processor.py
./chain_processors/example/rank_processor.py
./chain_processors/example/recall_processor.py
./chain_processors/frameworks/__init__.py
./chain_processors/frameworks/context_manager.py
./chain_processors/frameworks/processor.py
./chain_processors/frameworks/processor_chains.py
./chain_processors/frameworks/processor_dag.py
./chain_processors/frameworks/route_manager.py
./chain_processors/processors/__init__.py
./chain_processors/processors/concrect_processor.py
chain_processors_framework.egg-info/PKG-INFO
chain_processors_framework.egg-info/SOURCES.txt
chain_processors_framework.egg-info/dependency_links.txt
chain_processors_framework.egg-info/top_level.txt
chain_processors_framework.egg-info/zip-safe