Metadata-Version: 2.1
Name: chain-processors-framework
Version: 0.0.1
Summary: coding with a chain framework
Home-page: https://github.com/byscut/chain-processors-framework.git
Author: byscut
Author-email: byscut@foxmail.com
License: MIT
Platform: UNKNOWN
License-File: LICENSE
